[
  {
    "id": "sub-2026-07-09-45eecf61",
    "submittedAt": "2026-07-09T22:04:41.262Z",
    "submissionType": "Idea",
    "status": "New",
    "eventType": "",
    "eventName": "Idea submission",
    "locationName": "",
    "address": "",
    "city": "",
    "date": "2026-07-09T22:04:41.262Z",
    "startTime": "",
    "endTime": "",
    "ageRange": "",
    "costType": "",
    "costDetail": "",
    "cost": "",
    "signupRequirement": "",
    "signupLinkInfo": "",
    "eventDescription": "",
    "parentTips": "",
    "types": "make_filters_easier",
    "link": "",
    "additionalInfo": "",
    "internalNotes": "",
    "convertedEventId": "",
    "submittedByEmail": "",
    "requestedLocation": "",
    "sourceContext": "",
    "selectedCity": ""
  },
  {
    "id": "sub-2026-07-09-9f113a4a",
    "submittedAt": "2026-07-09T21:55:28.181Z",
    "submissionType": "Event",
    "status": "New",
    "eventType": "One-time event",
    "eventName": "Doodle and Discover Wednesdays",
    "locationName": "Oshman Family JCC - Jeff Center for Families - Building G room 106",
    "address": "",
    "city": "Palo Alto",
    "date": "2026-07-09T21:55:28.181Z",
    "startTime": "13:00",
    "endTime": "17:30",
    "ageRange": "2–5",
    "costType": "Free",
    "costDetail": "",
    "cost": "Free",
    "signupRequirement": "Registration required",
    "signupLinkInfo": "",
    "eventDescription": "This free arts and crafts activity is perfect for families with children aged 2–6. Register today, then drop in anytime between 1:00–5:30 PM on scheduled Wednesdays.\n\n\nJuly 1: Independence Day craft\n\n\nAug 5: Craft an ice cream cone\n\n\nSept. 2: Paper bag houses",
    "parentTips": "",
    "types": "",
    "link": "https://paloaltojcc.org/event-detail/es_1830684/?fbclid=IwVERDUAS89OFleHRuA2FlbQIxMABzcnRjBmFwcF9pZAwzNTA2ODU1MzE3MjgAAR79M9uwcnOX37J_NIY1kLk2y_VP9DtiMw7exgdLHZbKmXnLjpbE4t0qn1Cs1Q_aem__mzMtpe4BO-RJSlULOS6cQ",
    "additionalInfo": "",
    "internalNotes": "One-time event · Signup: Registration required",
    "convertedEventId": "",
    "submittedByEmail": "",
    "requestedLocation": "Oshman Family JCC - Jeff Center for Families - Building G room 106",
    "sourceContext": "",
    "selectedCity": ""
  }
]